yas/__init__.py
yas/core/__init__.py
yas/core/application.py
yas/core/client.py
yas/core/env_configuration.py
yas/core/errors.py
yas/core/handler_manager.py
yas/core/logging.py
yas/handlers/__init__.py
yas/handlers/default_handler.py
yas/handlers/help_handler.py
yas/handlers/identify_handler.py
yas/handlers/ignored_types_handler.py
yas/handlers/not_talking_to_bot_handler.py
yas/handlers/rules_handler.py
yas-2.0.dist-info/METADATA
yas-2.0.dist-info/WHEEL
yas-2.0.dist-info/entry_points.txt
yas-2.0.dist-info/top_level.txt
yas-2.0.dist-info/RECORD
